{
  "$schema": "https://developer.microsoft.com/json-schemas/fabric/item/report/definition/page/1.4.0/schema.json",
  "name": "ReportSectionb8aaba03a6008c1a40cd",
  "displayName": "Warpzone Design Exercise",
  "displayOption": "FitToPage",
  "height": 720,
  "width": 1280,
  "filterConfig": {
    "filters": [
      {
        "name": "Filter9242361d66d33c148c53",
        "field": {
          "Column": {
            "Expression": {
              "SourceRef": {
                "Entity": "Dates"
              }
            },
            "Property": "Year"
          }
        },
        "type": "Advanced",
        "filter": {
          "Version": 2,
          "From": [
            {
              "Name": "d",
              "Entity": "Dates",
              "Type": 0
            }
          ],
          "Where": [
            {
              "Condition": {
                "Comparison": {
                  "ComparisonKind": 0,
                  "Left": {
                    "Column": {
                      "Expression": {
                        "SourceRef": {
                          "Source": "d"
                        }
                      },
                      "Property": "Year"
                    }
                  },
                  "Right": {
                    "Literal": {
                      "Value": "2020L"
                    }
                  }
                }
              }
            }
          ]
        },
        "howCreated": "User"
      }
    ]
  }
}